Workbook

Sheet Assumptions
A1: SMALL BUSINESS P&L MODEL · ASSUMPTIONS & DRIVERS
A2: HeatingPro Services Pvt. Ltd. | FY 2024–2026 Projections
A4: COLOR LEGEND
B5: Blue text = Hard-coded input (change for scenarios) | C5: Black text = Formula (do not edit) | D5: Green text = Cross-sheet link | E5: Red text = External link
A7: REVENUE ASSUMPTIONS
B8: FY 2024A | C8: FY 2025E | D8: FY 2026E
A9: Installation Revenue (₹) | B9: 3200000 | C9: 3800000 | D9: 4500000
A10: AMC Contracts Revenue (₹) | B10: 1500000 | C10: 1900000 | D10: 2400000
A11: Repair & Service Revenue (₹) | B11: 800000 | C11: 950000 | D11: 1100000
A12: Revenue Growth YoY | C12: 0.175 | D12: 0.193
A14: COST ASSUMPTIONS (% of Total Revenue)
B15: FY 2024A | C15: FY 2025E | D15: FY 2026E
A16: Material / COGS % | B16: 0.38 | C16: 0.36 | D16: 0.34
A17: Labour Cost % | B17: 0.22 | C17: 0.21 | D17: 0.2
A18: Rent & Utilities % | B18: 0.05 | C18: 0.05 | D18: 0.04
A19: Marketing & Ads % | B19: 0.03 | C19: 0.04 | D19: 0.04
A20: Admin & Overheads % | B20: 0.04 | C20: 0.04 | D20: 0.03
A21: Depreciation % | B21: 0.02 | C21: 0.02 | D21: 0.02
A23: TAX & OTHER ASSUMPTIONS
B24: FY 2024A | C24: FY 2025E | D24: FY 2026E
A25: Corporate Tax Rate % | B25: 0.25 | C25: 0.25 | D25: 0.25
A26: Interest Expense (₹) | B26: 80000 | C26: 70000 | D26: 60000
A28: ★ All blue cells are inputs — change them to model different scenarios (e.g., revenue growth +5%, margins +2%)

Sheet P&L Model
A1: PROFIT & LOSS STATEMENT · HeatingPro Services Pvt. Ltd.
A2: All figures in ₹ | Inputs sourced from Assumptions sheet
A4: Line Item | B4: FY 2024A | C4: FY 2025E | D4: FY 2026E
A5: REVENUE
A6: Installation Revenue | B6: =Assumptions!B9 -> 3200000 | C6: =Assumptions!C9 -> 3800000 | D6: =Assumptions!D9 -> 4500000
A7: AMC Contracts Revenue | B7: =Assumptions!B10 -> 1500000 | C7: =Assumptions!C10 -> 1900000 | D7: =Assumptions!D10 -> 2400000
A8: Repair & Service Revenue | B8: =Assumptions!B11 -> 800000 | C8: =Assumptions!C11 -> 950000 | D8: =Assumptions!D11 -> 1100000
A9: TOTAL REVENUE | B9: =SUM(B6:B8) -> 5500000 | C9: =SUM(C6:C8) -> 6650000 | D9: =SUM(D6:D8) -> 8000000
A10: Revenue Growth % | B10: ="-" -> - | C10: =IFERROR((C9-B9)/B9,"-") -> 0.20909091 | D10: =IFERROR((D9-C9)/C9,"-") -> 0.20300752
A12: COST OF GOODS SOLD
A13: Material / COGS | B13: =B9*Assumptions!B16 -> 2090000 | C13: =C9*Assumptions!C16 -> 2394000 | D13: =D9*Assumptions!D16 -> 2720000
A14: Labour Cost | B14: =B9*Assumptions!B17 -> 1210000 | C14: =C9*Assumptions!C17 -> 1396500 | D14: =D9*Assumptions!D17 -> 1600000
A15: TOTAL COGS | B15: =SUM(B13:B14) -> 3300000 | C15: =SUM(C13:C14) -> 3790500 | D15: =SUM(D13:D14) -> 4320000
A17: GROSS PROFIT | B17: =B9-B15 -> 2200000 | C17: =C9-C15 -> 2859500 | D17: =D9-D15 -> 3680000
A18: Gross Margin % | B18: =IFERROR(B17/B9,0) -> 0.4 | C18: =IFERROR(C17/C9,0) -> 0.43 | D18: =IFERROR(D17/D9,0) -> 0.46
A20: OPERATING EXPENSES (OPEX)
A21: Rent & Utilities | B21: =B9*Assumptions!B18 -> 275000 | C21: =C9*Assumptions!C18 -> 332500 | D21: =D9*Assumptions!D18 -> 320000
A22: Marketing & Advertising | B22: =B9*Assumptions!B19 -> 165000 | C22: =C9*Assumptions!C19 -> 266000 | D22: =D9*Assumptions!D19 -> 320000
A23: Admin & Overheads | B23: =B9*Assumptions!B20 -> 220000 | C23: =C9*Assumptions!C20 -> 266000 | D23: =D9*Assumptions!D20 -> 240000
A24: Depreciation | B24: =B9*Assumptions!B21 -> 110000 | C24: =C9*Assumptions!C21 -> 133000 | D24: =D9*Assumptions!D21 -> 160000
A25: TOTAL OPEX | B25: =SUM(B21:B24) -> 770000 | C25: =SUM(C21:C24) -> 997500 | D25: =SUM(D21:D24) -> 1040000
A27: EBITDA (Gross Profit – OPEX + D&A) | B27: =B17-B25+B24 -> 1540000 | C27: =C17-C25+C24 -> 1995000 | D27: =D17-D25+D24 -> 2800000
A28: EBITDA Margin % | B28: =IFERROR(B27/B9,0) -> 0.28 | C28: =IFERROR(C27/C9,0) -> 0.3 | D28: =IFERROR(D27/D9,0) -> 0.35
A29: EBIT (Operating Profit) | B29: =B17-B25 -> 1430000 | C29: =C17-C25 -> 1862000 | D29: =D17-D25 -> 2640000
A30: EBIT Margin % | B30: =IFERROR(B29/B9,0) -> 0.26 | C30: =IFERROR(C29/C9,0) -> 0.28 | D30: =IFERROR(D29/D9,0) -> 0.33
A32: BELOW THE LINE
A33: Interest Expense | B33: =Assumptions!B26 -> 80000 | C33: =Assumptions!C26 -> 70000 | D33: =Assumptions!D26 -> 60000
A34: EBT (Earnings Before Tax) | B34: =B29-B33 -> 1350000 | C34: =C29-C33 -> 1792000 | D34: =D29-D33 -> 2580000
A35: Tax Expense | B35: =B34*Assumptions!B25 -> 337500 | C35: =C34*Assumptions!C25 -> 448000 | D35: =D34*Assumptions!D25 -> 645000
A37: NET PROFIT (PAT) | B37: =B34-B35 -> 1012500 | C37: =C34-C35 -> 1344000 | D37: =D34-D35 -> 1935000
A38: Net Profit Margin % | B38: =IFERROR(B37/B9,0) -> 0.18409091 | C38: =IFERROR(C37/C9,0) -> 0.20210526 | D38: =IFERROR(D37/D9,0) -> 0.241875
A40: ★ Go to the Assumptions sheet to change inputs — this model recalculates automatically.

Sheet Scenario Analysis
A1: SCENARIO ANALYSIS · FY 2025 Projections
A3: Metric | B3: Bear Case | C3: Base Case | D3: Bull Case
A4: KEY ASSUMPTION
A5: Revenue Growth Assumption | B5: 0.08 | C5: 0.175 | D5: 0.28
A6: Gross Margin Assumption | B6: 0.36 | C6: 0.4 | D6: 0.44
A7: OPEX % of Revenue | B7: 0.18 | C7: 0.15 | D7: 0.12
A9: OUTPUT PROJECTIONS (FY 2025E)
A10: Total Revenue (₹) | B10: =(5500000)*(1+B5) -> 5940000 | C10: =(5500000)*(1+C5) -> 6462500 | D10: =(5500000)*(1+D5) -> 7040000
A11: Gross Profit (₹) | B11: =B10*B6 -> 2138400 | C11: =C10*C6 -> 2585000 | D11: =D10*D6 -> 3097600
A12: Gross Margin % | B12: =B6 -> 0.36 | C12: =C6 -> 0.4 | D12: =D6 -> 0.44
A13: OPEX (₹) | B13: =B10*B7 -> 1069200 | C13: =C10*C7 -> 969375 | D13: =D10*D7 -> 844800
A14: EBIT (₹) | B14: =B11-B13 -> 1069200 | C14: =C11-C13 -> 1615625 | D14: =D11-D13 -> 2252800
A15: Net Profit (₹) @25% tax | B15: =B14*(1-0.25) -> 801900 | C15: =C14*(1-0.25) -> 1211718.8 | D15: =D14*(1-0.25) -> 1689600
A16: Net Margin % | B16: =IFERROR(B15/B10,0) -> 0.135 | C16: =IFERROR(C15/C10,0) -> 0.1875 | D16: =IFERROR(D15/D10,0) -> 0.24

Sheet Dashboard
A1: MANAGEMENT DASHBOARD · HeatingPro Services Pvt. Ltd.
A2: Key performance indicators · Data sourced from P&L Model sheet
B4: Total Revenue | E4: Gross Profit | H4: EBIT | K4: Net Profit
B5: FY24A | C5: FY25E | D5: FY26E | E5: FY24A | F5: FY25E | G5: FY26E | H5: FY24A | I5: FY25E | J5: FY26E | K5: FY24A | L5: FY25E | M5: FY26E
B6: ='P&L Model'!B9 -> 5500000 | C6: ='P&L Model'!C9 -> 6650000 | D6: ='P&L Model'!D9 -> 8000000 | E6: ='P&L Model'!B17 -> 2200000 | F6: ='P&L Model'!C17 -> 2859500 | G6: ='P&L Model'!D17 -> 3680000 | H6: ='P&L Model'!B29 -> 1430000 | I6: ='P&L Model'!C29 -> 1862000 | J6: ='P&L Model'!D29 -> 2640000 | K6: ='P&L Model'!B37 -> 1012500 | L6: ='P&L Model'!C37 -> 1344000 | M6: ='P&L Model'!D37 -> 1935000
B9: FY 2024A | C9: FY 2025E | D9: FY 2026E
A10: Total Revenue | B10: ='P&L Model'!B9 -> 5500000 | C10: ='P&L Model'!C9 -> 6650000 | D10: ='P&L Model'!D9 -> 8000000
A11: Gross Profit | B11: ='P&L Model'!B17 -> 2200000 | C11: ='P&L Model'!C17 -> 2859500 | D11: ='P&L Model'!D17 -> 3680000
A12: EBIT | B12: ='P&L Model'!B29 -> 1430000 | C12: ='P&L Model'!C29 -> 1862000 | D12: ='P&L Model'!D29 -> 2640000
A13: Net Profit | B13: ='P&L Model'!B37 -> 1012500 | C13: ='P&L Model'!C37 -> 1344000 | D13: ='P&L Model'!D37 -> 1935000
B27: FY 2024A | C27: FY 2025E | D27: FY 2026E
A28: Gross Margin % | B28: ='P&L Model'!B18 -> 0.4 | C28: ='P&L Model'!C18 -> 0.43 | D28: ='P&L Model'!D18 -> 0.46
A29: EBIT Margin % | B29: ='P&L Model'!B30 -> 0.26 | C29: ='P&L Model'!C30 -> 0.28 | D29: ='P&L Model'!D30 -> 0.33
A30: Net Margin % | B30: ='P&L Model'!B38 -> 0.18409091 | C30: ='P&L Model'!C38 -> 0.20210526 | D30: ='P&L Model'!D38 -> 0.241875
